nectar_osc/__init__.py
nectar_osc/compute.py
nectar_osc/config.py
nectar_osc/freshdesk.py
nectar_osc/identity.py
nectar_osc/mailout.py
nectar_osc/network.py
nectar_osc/plugin.py
nectar_osc/rating.py
nectar_osc/security.py
nectar_osc/show.py
nectar_osc/util.py
nectar_osc/templates/README.rst
nectar_osc/templates/outage-notification.tmpl
nectar_osc/tests/__init__.py
nectar_osc/tests/nectar-osc.conf
nectar_osc/tests/test.py
nectar_osc/tests/unit/__init__.py
nectar_osc/tests/unit/fakes.py
nectar_osc/tests/unit/test_compute.py
nectar_osc/tests/unit/test_identity.py
nectar_osc/tests/unit/test_mailout.py
nectar_osc/tests/unit/test_plugin.py
nectar_osc/tests/unit/test_util.py
nectar_osc-1.3.0.dist-info/licenses/LICENSE
nectar_osc-1.3.0.dist-info/METADATA
nectar_osc-1.3.0.dist-info/WHEEL
nectar_osc-1.3.0.dist-info/entry_points.txt
nectar_osc-1.3.0.dist-info/pbr.json
nectar_osc-1.3.0.dist-info/top_level.txt
nectar_osc-1.3.0.dist-info/RECORD
