Metadata-Version: 2.4
Name: nectar-osc
Version: 1.3.0
Summary: OpenStack client plugin for misc Nectar tooling
Home-page: https://github.com/NeCTAR-RC/python-nectar-osc
Author: ARDC Nectar Cloud Services
Author-email: coreservices@ardc.edu.au
License: Apache-2.0
Classifier: Environment :: OpenStack
Classifier: Intended Audience :: Information Technology
Classifier: Intended Audience :: System Administrators
Classifier: License :: OSI Approved :: Apache Software License
Classifier: Operating System :: POSIX :: Linux
Classifier: Programming Language :: Python
Classifier: Programming Language :: Python :: 3 :: Only
Classifier: Programming Language :: Python :: 3
Classifier: Programming Language :: Python :: 3.10
Classifier: Programming Language :: Python :: 3.12
License-File: LICENSE
Requires-Dist: oslo.config
Requires-Dist: oslo.utils
Requires-Dist: osc-lib
Requires-Dist: keystoneauth1
Requires-Dist: python-freshdesk
Requires-Dist: openstacksdk>=4.4.0
Requires-Dist: python-openstackclient>=7.4.0
Requires-Dist: python-cloudkittyclient
Requires-Dist: python-neutronclient
Requires-Dist: python-keystoneclient
Requires-Dist: nectarclient-lib
Requires-Dist: pbr>=3.0.0
Requires-Dist: jinja2
Dynamic: author
Dynamic: author-email
Dynamic: classifier
Dynamic: description
Dynamic: description-content-type
Dynamic: home-page
Dynamic: license
Dynamic: license-file
Dynamic: requires-dist
Dynamic: summary
